rmqrcode/__init__.py
rmqrcode/console.py
rmqrcode/errors.py
rmqrcode/qr_image.py
rmqrcode/rmqrcode.py
rmqrcode/segments.py
rmqrcode/encoder/__init__.py
rmqrcode/encoder/alphanumeric_encoder.py
rmqrcode/encoder/byte_encoder.py
rmqrcode/encoder/encoder_base.py
rmqrcode/encoder/kanji_encoder.py
rmqrcode/encoder/numeric_encoder.py
rmqrcode/enums/__init__.py
rmqrcode/enums/color.py
rmqrcode/enums/fit_strategy.py
rmqrcode/format/__init__.py
rmqrcode/format/alignment_pattern_coordinates.py
rmqrcode/format/error_correction_level.py
rmqrcode/format/generator_polynomials.py
rmqrcode/format/mask.py
rmqrcode/format/rmqr_versions.py
rmqrcode/util/__init__.py
rmqrcode/util/error_correction.py
rmqrcode/util/galois_fields.py
rmqrcode/util/utilities.py
rmqrcode-0.3.2.dist-info/LICENSE
rmqrcode-0.3.2.dist-info/METADATA
rmqrcode-0.3.2.dist-info/WHEEL
rmqrcode-0.3.2.dist-info/entry_points.txt
rmqrcode-0.3.2.dist-info/top_level.txt
rmqrcode-0.3.2.dist-info/RECORD
