Metadata-Version: 2.1
Name: rmqrcode
Version: 0.3.2
Summary: An rMQR Code Generetor
Home-page: https://github.com/OUDON/rmqrcode
Author: Takahiro Tomita
Author-email: ttp8101@gmail.com
Classifier: Programming Language :: Python :: 3
Classifier: License :: OSI Approved :: MIT License
Classifier: Operating System :: OS Independent
Requires-Python: >=3.7
License-File: LICENSE
Requires-Dist: Pillow
Provides-Extra: dev
Requires-Dist: pytest ; extra == 'dev'
Requires-Dist: flake8 ; extra == 'dev'
Requires-Dist: isort ; extra == 'dev'
Requires-Dist: black ; extra == 'dev'
